djangocms_blog/cms_helpers.py
djangocms_blog/models.py
djangocms_blog/__init__.py
djangocms_blog/urls.py
djangocms_blog/compat.py
djangocms_blog/managers.py
djangocms_blog/settings.py
djangocms_blog/admin.py
djangocms_blog/forms.py
djangocms_blog/feeds.py
djangocms_blog/cms_plugins.py
djangocms_blog/cms_toolbar.py
djangocms_blog/views.py
djangocms_blog/menu.py
djangocms_blog/cms_app.py
djangocms_blog/static/djangocms_blog/css/djangocms_blog_admin.css
djangocms_blog/static/djangocms_blog/css/djangocms_blog.css
djangocms_blog/sitemaps/__init__.py
djangocms_blog/south_migrations/0002_auto__del_blogcategorytranslation__del_unique_blogcategorytranslation_.py
djangocms_blog/south_migrations/0004_auto__add_field_posttranslation_meta_description.py
djangocms_blog/south_migrations/0007_auto__add_field_posttranslation_post_text.py
djangocms_blog/south_migrations/__init__.py
djangocms_blog/south_migrations/0005_auto__add_field_posttranslation_meta_keywords.py
djangocms_blog/south_migrations/0009_auto.py
djangocms_blog/south_migrations/0008_auto__add_field_posttranslation_meta_title.py
djangocms_blog/south_migrations/0006_auto__add_field_post_enable_comments.py
djangocms_blog/south_migrations/0001_initial.py
djangocms_blog/south_migrations/0011_chg_field_post_translation_abstract.py
djangocms_blog/south_migrations/0003_rename_plugins.py
djangocms_blog/south_migrations/0010_auto__chg_field_post_main_image_full__chg_field_post_main_image__chg_f.py
djangocms_blog/templates/djangocms_blog/base.html
djangocms_blog/templates/djangocms_blog/post_detail.html
djangocms_blog/templates/djangocms_blog/post_archive.html
djangocms_blog/templates/djangocms_blog/post_list.html
djangocms_blog/templates/djangocms_blog/plugins/archive.html
djangocms_blog/templates/djangocms_blog/plugins/latest_entries.html
djangocms_blog/templates/djangocms_blog/plugins/tags.html
djangocms_blog/templates/djangocms_blog/plugins/categories.html
djangocms_blog_martin-0.5.1.dev3.dist-info/METADATA
djangocms_blog_martin-0.5.1.dev3.dist-info/LICENSE.txt
djangocms_blog_martin-0.5.1.dev3.dist-info/top_level.txt
djangocms_blog_martin-0.5.1.dev3.dist-info/metadata.json
djangocms_blog_martin-0.5.1.dev3.dist-info/RECORD
djangocms_blog_martin-0.5.1.dev3.dist-info/DESCRIPTION.rst
djangocms_blog_martin-0.5.1.dev3.dist-info/WHEEL
