Metadata-Version: 2.0
Name: djangocms-blog-martin
Version: 0.5.1.dev3
Summary: Fork of djangoCMS 3 blog application
Home-page: https://github.com/marty3d/djangocms-blog/
Author: Iacopo Spalletti, Martin Kjellberg
Author-email: i.spalletti@nephila.it
License: BSD
Keywords: djangocms-blog,blog,django,wordpress,multilingual
Platform: UNKNOWN
Classifier: Development Status :: 4 - Beta
Classifier: Framework :: Django
Classifier: Intended Audience :: Developers
Classifier: License :: OSI Approved :: BSD License
Classifier: Natural Language :: English
Classifier: Framework :: Django
Classifier: Framework :: Django :: 1.6
Classifier: Framework :: Django :: 1.7
Classifier: Framework :: Django :: 1.8
Classifier: Programming Language :: Python :: 2
Classifier: Programming Language :: Python :: 2.6
Classifier: Programming Language :: Python :: 2.7
Classifier: Programming Language :: Python :: 3
Classifier: Programming Language :: Python :: 3.3
Classifier: Programming Language :: Python :: 3.4
Requires-Dist: django-parler (>=1.2)
Requires-Dist: django-cms (>=3.0)
Requires-Dist: django-taggit (>=0.12.2)
Requires-Dist: django-filer
Requires-Dist: pytz
Requires-Dist: django-taggit-templatetags
Requires-Dist: django-taggit-autosuggest
Requires-Dist: djangocms-text-ckeditor
Requires-Dist: cmsplugin-filer
Requires-Dist: django-meta (>=0.2)
Requires-Dist: django-meta-mixin (>=0.1.1)
Provides-Extra: admin-enhancer
Requires-Dist: django-admin-enhancer; extra == 'admin-enhancer'
